mcp_bridge/__init__.py
mcp_bridge/endpoints.py
mcp_bridge/lifespan.py
mcp_bridge/main.py
mcp_bridge/openapi_tags.py
mcp_bridge/py.typed
mcp_bridge/config/__init__.py
mcp_bridge/config/env_subst.py
mcp_bridge/config/file.py
mcp_bridge/config/final.py
mcp_bridge/config/http.py
mcp_bridge/config/initial.py
mcp_bridge/health/__init__.py
mcp_bridge/health/manager.py
mcp_bridge/health/router.py
mcp_bridge/health/types.py
mcp_bridge/mcpManagement/__init__.py
mcp_bridge/mcpManagement/prompts.py
mcp_bridge/mcpManagement/resources.py
mcp_bridge/mcpManagement/router.py
mcp_bridge/mcpManagement/server.py
mcp_bridge/mcpManagement/tools.py
mcp_bridge/mcp_clients/AbstractClient.py
mcp_bridge/mcp_clients/DockerClient.py
mcp_bridge/mcp_clients/McpClientManager.py
mcp_bridge/mcp_clients/SseClient.py
mcp_bridge/mcp_clients/StdioClient.py
mcp_bridge/mcp_clients/session.py
mcp_bridge/mcp_server/__init__.py
mcp_bridge/mcp_server/server.py
mcp_bridge/mcp_server/sse.py
mcp_bridge/mcp_server/sse_transport.py
mcp_bridge/models/__init__.py
mcp_bridge/models/chatCompletionStreamResponse.py
mcp_bridge/models/mcpServerStatus.py
mcp_bridge/openai_clients/__init__.py
mcp_bridge/openai_clients/chatCompletion.py
mcp_bridge/openai_clients/completion.py
mcp_bridge/openai_clients/genericHttpxClient.py
mcp_bridge/openai_clients/streamChatCompletion.py
mcp_bridge/openai_clients/streamCompletion.py
mcp_bridge/openai_clients/utils.py
mcp_bridge/sampling/modelSelector.py
mcp_bridge/sampling/sampler.py
mcp_bridge/tool_mappers/__init__.py
mcp_bridge/tool_mappers/mcp2openaiConverters.py
mcp_bridge/tool_mappers/openai2mcpConverters.py
mcp_bridge-0.5.0.dist-info/METADATA
mcp_bridge-0.5.0.dist-info/WHEEL
mcp_bridge-0.5.0.dist-info/entry_points.txt
mcp_bridge-0.5.0.dist-info/licenses/LICENSE
mcp_bridge-0.5.0.dist-info/RECORD
