Metadata-Version: 2.4
Name: mcp-bridge
Version: 0.5.0
Summary: A middleware to provide an openAI compatible endpoint that can call MCP tools.
License-File: LICENSE
Requires-Python: >=3.11
Requires-Dist: deepmerge>=2.0
Requires-Dist: fastapi>=0.115.6
Requires-Dist: httpx-sse>=0.4.0
Requires-Dist: httpx>=0.28.1
Requires-Dist: lmos-openai-types
Requires-Dist: loguru>=0.7.3
Requires-Dist: mcp>=1.2.0
Requires-Dist: mcpx[docker]>=0.1.1
Requires-Dist: pydantic-settings>=2.7.0
Requires-Dist: pydantic>=2.10.4
Requires-Dist: sse-starlette>=2.2.0
Requires-Dist: tortoise-orm[asyncmy,asyncpg]>=0.23.0
Requires-Dist: uvicorn>=0.34.0
